{
  "Character_Id": 10091,
  "Dev_Name": "CH0250",
  "Prefab_Name": "LobbyCH0250",
  "Texture_Path": "Assets/_MX/AddressableAsset/UIs/01_Common/08_Lobbyillust/Lobbyillust_Icon_CH0250_01.png",
  "BGM_Id": 210,
  "Bundles": {
    "Entries": [
      {
        "Region": 3,
        "Platform": 2,
        "Main_Bundle": "ui-uilobbyelement-_mxload-prefabs-2025-07-02_assets_all_869785087.bundle",
        "Resource_Bundle_List": [
          "AssetBundles\\assets-_mx-spinelobbies-ch0250_home-_mxdependency-assets-2025-07-02_assets_all_49300471.bundle",
          "AssetBundles\\assets-_mx-spinelobbies-ch0250_home-_mxdependency-timelines-2025-07-02_assets_all_1608396734.bundle",
          "AssetBundles\\assets-_mx-spinelobbies-ch0250_home-_mxdependency-textures-2025-07-02_assets_all_1071383787.bundle",
          "AssetBundles\\assets-_mx-spinelobbies-ch0250_home-_mxdependency-textassets-2025-07-02_assets_all_3088824996.bundle",
          "AssetBundles\\assets-_mx-spinelobbies-ch0250_home-_mxdependency-materials-2025-07-02_assets_all_3594604763.bundle"
        ],
        "Dependency_Bundle_List": [
          "MX_monoscripts_3981838347.bundle",
          "assets-_mx-spinelobbies-_mxcommon-_mxdependency-materials-2025-07-02_assets_all_149539334.bundle",
          "assets-_mx-spinelobbies-_mxcommon-_mxdependency-assets-2025-07-02_assets_all_3657483517.bundle",
          "MX_unitybuiltinshaders_4156112658.bundle",
          "assets-_mx-spinelobbies-_mxcommon-_mxdependency-textures-2025-07-02_assets_all_1219719739.bundle",
          "prologgroup-assets-_mx-addressableasset-audio-audiomixer-_mxprolog-2025-07-02_assets_all_2266188573.bundle",
          "assets-_mx-spinelobbies-_mxcommon-_mxdependency-audio-2025-07-02_assets_all_1236838282.bundle",
          "assets-_mx-shaders-_mxdependency-shaders-2025-07-02_assets_all_3046151907.bundle",
          "prologdepengroup-assets-_mx-shaders-_mxprolog-2025-07-02_assets_all_222426929.bundle",
          "prologdepengroup-assets-ngui-resources-shaders-_mxprolog-2025-07-02_assets_all_1067322330.bundle",
          "audio-sfx_backgroundeffect-_mxload-audio-2025-07-02_assets_all_4023696992.bundle",
          "prologdepengroup-assets-_mx-uis-atlas-_mxprolog-2025-07-02_assets_all_3359745090.bundle"
        ]
      }
    ]
  },
  "Audios": {
    "Entries": [
      {
        "Region": 3,
        "Audio_Path_List": [
          "MediaResources\\Audio\\VOC_JP\\ch0250_memoriallobby_1_1.ogg",
          "MediaResources\\Audio\\VOC_JP\\ch0250_memoriallobby_1_2.ogg",
          "MediaResources\\Audio\\VOC_JP\\ch0250_memoriallobby_2_1.ogg",
          "MediaResources\\Audio\\VOC_JP\\ch0250_memoriallobby_2_2.ogg",
          "MediaResources\\Audio\\VOC_JP\\ch0250_memoriallobby_3_1.ogg",
          "MediaResources\\Audio\\VOC_JP\\ch0250_memoriallobby_3_2.ogg",
          "MediaResources\\Audio\\VOC_JP\\ch0250_memoriallobby_4_1.ogg",
          "MediaResources\\Audio\\VOC_JP\\ch0250_memoriallobby_4_2.ogg",
          "MediaResources\\Audio\\VOC_JP\\ch0250_memoriallobby_5_1.ogg",
          "MediaResources\\Audio\\VOC_JP\\ch0250_memoriallobby_5_2.ogg",
          "MediaResources\\Audio\\VOC_JP\\ch0250_memoriallobby_5_3.ogg"
        ]
      }
    ]
  },
  "Subtitles": {
    "Entries": [
      {
        "Region": 3,
        "CharacterDialogInfo_List": [
          {
            "CharacterId": 10091,
            "CostumeUniqueId": 1009101,
            "DisplayOrder": 300,
            "DialogCategory": 8,
            "DialogCondition": 0,
            "GroupId": 1,
            "ActionName": "",
            "DialogType": 0,
            "Duration": 6700,
            "LocalizeKR": "……자, 빨리!",
            "LocalizeJP": "……ほら、早く！",
            "VoiceIds": [],
            "CollectionVisible": false,
            "CVCollectionType": 0,
            "LocalizeCVGroup": "CVGroup_UILobbySpecial_Idle1",
            "AnimationName": "Talk_01_M",
            "Anniversary": 0,
            "StartDate": "",
            "EndDate": "",
            "ApplyPosition": false,
            "PosX": 0.0,
            "PosY": 0.0,
            "UnlockFavorRank": 0,
            "UnlockEquipWeapon": false
          },
          {
            "CharacterId": 10091,
            "CostumeUniqueId": 1009101,
            "DisplayOrder": 310,
            "DialogCategory": 8,
            "DialogCondition": 0,
            "GroupId": 1,
            "ActionName": "",
            "DialogType": 0,
            "Duration": 9400,
            "LocalizeKR": "아~ 해봐!\n떨어지기 전에!",
            "LocalizeJP": "あ～んして！\n落ちる前に！",
            "VoiceIds": [],
            "CollectionVisible": false,
            "CVCollectionType": 0,
            "LocalizeCVGroup": "CVGroup_UILobbySpecial_Idle1",
            "AnimationName": "",
            "Anniversary": 0,
            "StartDate": "",
            "EndDate": "",
            "ApplyPosition": false,
            "PosX": 0.0,
            "PosY": 0.0,
            "UnlockFavorRank": 0,
            "UnlockEquipWeapon": false
          },
          {
            "CharacterId": 10091,
            "CostumeUniqueId": 1009101,
            "DisplayOrder": 320,
            "DialogCategory": 8,
            "DialogCondition": 0,
            "GroupId": 2,
            "ActionName": "",
            "DialogType": 0,
            "Duration": 6870,
            "LocalizeKR": "선생님이 안 먹어주면,\n나도 못 먹으니까!",
            "LocalizeJP": "先生が食べてくれないと、\n私も食べらんないから！",
            "VoiceIds": [],
            "CollectionVisible": false,
            "CVCollectionType": 0,
            "LocalizeCVGroup": "CVGroup_UILobbySpecial_Idle2",
            "AnimationName": "Talk_02_M",
            "Anniversary": 0,
            "StartDate": "",
            "EndDate": "",
            "ApplyPosition": false,
            "PosX": 0.0,
            "PosY": 0.0,
            "UnlockFavorRank": 0,
            "UnlockEquipWeapon": false
          },
          {
            "CharacterId": 10091,
            "CostumeUniqueId": 1009101,
            "DisplayOrder": 330,
            "DialogCategory": 8,
            "DialogCondition": 0,
            "GroupId": 2,
            "ActionName": "",
            "DialogType": 0,
            "Duration": 9300,
            "LocalizeKR": "자, 아~!",
            "LocalizeJP": "はい、あ～ん！",
            "VoiceIds": [],
            "CollectionVisible": false,
            "CVCollectionType": 0,
            "LocalizeCVGroup": "CVGroup_UILobbySpecial_Idle2",
            "AnimationName": "",
            "Anniversary": 0,
            "StartDate": "",
            "EndDate": "",
            "ApplyPosition": false,
            "PosX": 0.0,
            "PosY": 0.0,
            "UnlockFavorRank": 0,
            "UnlockEquipWeapon": false
          },
          {
            "CharacterId": 10091,
            "CostumeUniqueId": 1009101,
            "DisplayOrder": 340,
            "DialogCategory": 8,
            "DialogCondition": 0,
            "GroupId": 3,
            "ActionName": "",
            "DialogType": 0,
            "Duration": 2970,
            "LocalizeKR": "……응?",
            "LocalizeJP": "……え？",
            "VoiceIds": [],
            "CollectionVisible": false,
            "CVCollectionType": 0,
            "LocalizeCVGroup": "CVGroup_UILobbySpecial_Idle3",
            "AnimationName": "Talk_03_M",
            "Anniversary": 0,
            "StartDate": "",
            "EndDate": "",
            "ApplyPosition": false,
            "PosX": 0.0,
            "PosY": 0.0,
            "UnlockFavorRank": 0,
            "UnlockEquipWeapon": false
          },
          {
            "CharacterId": 10091,
            "CostumeUniqueId": 1009101,
            "DisplayOrder": 350,
            "DialogCategory": 8,
            "DialogCondition": 0,
            "GroupId": 3,
            "ActionName": "",
            "DialogType": 0,
            "Duration": 13780,
            "LocalizeKR": "괜찮아?\n먼저 먹으라고...?",
            "LocalizeJP": "大丈夫？先に食べて……？",
            "VoiceIds": [],
            "CollectionVisible": false,
            "CVCollectionType": 0,
            "LocalizeCVGroup": "CVGroup_UILobbySpecial_Idle3",
            "AnimationName": "",
            "Anniversary": 0,
            "StartDate": "",
            "EndDate": "",
            "ApplyPosition": false,
            "PosX": 0.0,
            "PosY": 0.0,
            "UnlockFavorRank": 0,
            "UnlockEquipWeapon": false
          },
          {
            "CharacterId": 10091,
            "CostumeUniqueId": 1009101,
            "DisplayOrder": 360,
            "DialogCategory": 8,
            "DialogCondition": 0,
            "GroupId": 4,
            "ActionName": "",
            "DialogType": 0,
            "Duration": 7610,
            "LocalizeKR": "어…?\n이 스푼, 카즈사꺼고?",
            "LocalizeJP": "え……？このスプーン、\nカズサのだし？",
            "VoiceIds": [],
            "CollectionVisible": false,
            "CVCollectionType": 0,
            "LocalizeCVGroup": "CVGroup_UILobbySpecial_Idle4",
            "AnimationName": "Talk_04_M",
            "Anniversary": 0,
            "StartDate": "",
            "EndDate": "",
            "ApplyPosition": false,
            "PosX": 0.0,
            "PosY": 0.0,
            "UnlockFavorRank": 0,
            "UnlockEquipWeapon": false
          },
          {
            "CharacterId": 10091,
            "CostumeUniqueId": 1009101,
            "DisplayOrder": 370,
            "DialogCategory": 8,
            "DialogCondition": 0,
            "GroupId": 4,
            "ActionName": "",
            "DialogType": 0,
            "Duration": 13320,
            "LocalizeKR": "……응?\n……어라?",
            "LocalizeJP": "……へ？\n……あれ？",
            "VoiceIds": [],
            "CollectionVisible": false,
            "CVCollectionType": 0,
            "LocalizeCVGroup": "CVGroup_UILobbySpecial_Idle4",
            "AnimationName": "",
            "Anniversary": 0,
            "StartDate": "",
            "EndDate": "",
            "ApplyPosition": false,
            "PosX": 0.0,
            "PosY": 0.0,
            "UnlockFavorRank": 0,
            "UnlockEquipWeapon": false
          },
          {
            "CharacterId": 10091,
            "CostumeUniqueId": 1009101,
            "DisplayOrder": 380,
            "DialogCategory": 8,
            "DialogCondition": 0,
            "GroupId": 5,
            "ActionName": "",
            "DialogType": 0,
            "Duration": 7650,
            "LocalizeKR": "스푼……?\n내꺼……?",
            "LocalizeJP": "スプーン……？\n私の……？",
            "VoiceIds": [],
            "CollectionVisible": false,
            "CVCollectionType": 0,
            "LocalizeCVGroup": "CVGroup_UILobbySpecial_Idle5",
            "AnimationName": "Talk_05_M",
            "Anniversary": 0,
            "StartDate": "",
            "EndDate": "",
            "ApplyPosition": false,
            "PosX": 0.0,
            "PosY": 0.0,
            "UnlockFavorRank": 0,
            "UnlockEquipWeapon": false
          },
          {
            "CharacterId": 10091,
            "CostumeUniqueId": 1009101,
            "DisplayOrder": 390,
            "DialogCategory": 8,
            "DialogCondition": 0,
            "GroupId": 5,
            "ActionName": "",
            "DialogType": 0,
            "Duration": 1770,
            "LocalizeKR": "……어.",
            "LocalizeJP": "……あ。",
            "VoiceIds": [],
            "CollectionVisible": false,
            "CVCollectionType": 0,
            "LocalizeCVGroup": "CVGroup_UILobbySpecial_Idle5",
            "AnimationName": "",
            "Anniversary": 0,
            "StartDate": "",
            "EndDate": "",
            "ApplyPosition": false,
            "PosX": 0.0,
            "PosY": 0.0,
            "UnlockFavorRank": 0,
            "UnlockEquipWeapon": false
          },
          {
            "CharacterId": 10091,
            "CostumeUniqueId": 1009101,
            "DisplayOrder": 400,
            "DialogCategory": 8,
            "DialogCondition": 0,
            "GroupId": 5,
            "ActionName": "",
            "DialogType": 0,
            "Duration": 12630,
            "LocalizeKR": "우와아아아!? \n방금 한 말 취소!",
            "LocalizeJP": "うわああああぁ！？\n今のナシ！",
            "VoiceIds": [],
            "CollectionVisible": false,
            "CVCollectionType": 0,
            "LocalizeCVGroup": "CVGroup_UILobbySpecial_Idle5",
            "AnimationName": "",
            "Anniversary": 0,
            "StartDate": "",
            "EndDate": "",
            "ApplyPosition": false,
            "PosX": 0.0,
            "PosY": 0.0,
            "UnlockFavorRank": 0,
            "UnlockEquipWeapon": false
          }
        ],
        "ScenarioScriptExcel_List": [
          {
            "ByteBuffer": {
              "Position": 0,
              "Length": 112
            },
            "GroupId": 1009103,
            "SelectionGroup": 0,
            "BGMId": 210,
            "Sound": "",
            "Transition": 2482233134,
            "BGName": 495330137,
            "BGEffect": 0,
            "PopupFileName": "",
            "ScriptKr": "#all;hide",
            "TextJp": "",
            "VoiceId": 0
          },
          {
            "ByteBuffer": {
              "Position": 0,
              "Length": 96
            },
            "GroupId": 1009103,
            "SelectionGroup": 0,
            "BGMId": 0,
            "Sound": "",
            "Transition": 0,
            "BGName": 0,
            "BGEffect": 0,
            "PopupFileName": "",
            "ScriptKr": "#wait;15000",
            "TextJp": "",
            "VoiceId": 0
          },
          {
            "ByteBuffer": {
              "Position": 0,
              "Length": 280
            },
            "GroupId": 1009103,
            "SelectionGroup": 0,
            "BGMId": 0,
            "Sound": "",
            "Transition": 0,
            "BGName": 510179268,
            "BGEffect": 0,
            "PopupFileName": "",
            "ScriptKr": "#st;[-1200,-530];serial;60;[wa:1000]― [log=카즈사 밴드]……[wa:2290]자, [wa:1090]빨리![/log]",
            "TextJp": "[wa:1000]― [log=카즈사 밴드]……[wa:2290]ほら、[wa:1090]早く！[/log]",
            "VoiceId": 0
          },
          {
            "ByteBuffer": {
              "Position": 0,
              "Length": 96
            },
            "GroupId": 1009103,
            "SelectionGroup": 0,
            "BGMId": 0,
            "Sound": "",
            "Transition": 0,
            "BGName": 0,
            "BGEffect": 0,
            "PopupFileName": "",
            "ScriptKr": "#wait;2220",
            "TextJp": "",
            "VoiceId": 0
          },
          {
            "ByteBuffer": {
              "Position": 0,
              "Length": 96
            },
            "GroupId": 1009103,
            "SelectionGroup": 0,
            "BGMId": 0,
            "Sound": "",
            "Transition": 0,
            "BGName": 0,
            "BGEffect": 0,
            "PopupFileName": "",
            "ScriptKr": "#clearST",
            "TextJp": "",
            "VoiceId": 0
          },
          {
            "ByteBuffer": {
              "Position": 0,
              "Length": 240
            },
            "GroupId": 1009103,
            "SelectionGroup": 0,
            "BGMId": 0,
            "Sound": "",
            "Transition": 0,
            "BGName": 0,
            "BGEffect": 0,
            "PopupFileName": "",
            "ScriptKr": "#st;[-1200,-530];serial;60;[wa:835]― [log=카즈사 밴드]아~[wa:615] 해봐![/log]",
            "TextJp": "[wa:835]― [log=카즈사 밴드]あ～ん[wa:615]して！[/log]",
            "VoiceId": 0
          },
          {
            "ByteBuffer": {
              "Position": 0,
              "Length": 232
            },
            "GroupId": 1009103,
            "SelectionGroup": 0,
            "BGMId": 0,
            "Sound": "",
            "Transition": 0,
            "BGName": 0,
            "BGEffect": 0,
            "PopupFileName": "",
            "ScriptKr": "#st;[-1200,-630];serial;60;[wa:800]― [log=카즈사 밴드]떨어지기 전에![/log]",
            "TextJp": "[wa:800]― [log=카즈사 밴드]落ちる前に！[/log]",
            "VoiceId": 0
          },
          {
            "ByteBuffer": {
              "Position": 0,
              "Length": 96
            },
            "GroupId": 1009103,
            "SelectionGroup": 0,
            "BGMId": 0,
            "Sound": "",
            "Transition": 0,
            "BGName": 0,
            "BGEffect": 0,
            "PopupFileName": "",
            "ScriptKr": "#wait;6150",
            "TextJp": "",
            "VoiceId": 0
          },
          {
            "ByteBuffer": {
              "Position": 0,
              "Length": 96
            },
            "GroupId": 1009103,
            "SelectionGroup": 0,
            "BGMId": 0,
            "Sound": "",
            "Transition": 0,
            "BGName": 0,
            "BGEffect": 0,
            "PopupFileName": "",
            "ScriptKr": "#clearST",
            "TextJp": "",
            "VoiceId": 0
          },
          {
            "ByteBuffer": {
              "Position": 0,
              "Length": 272
            },
            "GroupId": 1009103,
            "SelectionGroup": 0,
            "BGMId": 0,
            "Sound": "",
            "Transition": 0,
            "BGName": 2980401360,
            "BGEffect": 0,
            "PopupFileName": "",
            "ScriptKr": "#st;[-1200,-530];serial;60;[wa:1120]― [log=카즈사 밴드]선생님이 안 먹어주면,[/log]",
            "TextJp": "[wa:1120]― [log=카즈사 밴드]先生が食べてくれないと、[/log]",
            "VoiceId": 0
          },
          {
            "ByteBuffer": {
              "Position": 0,
              "Length": 256
            },
            "GroupId": 1009103,
            "SelectionGroup": 0,
            "BGMId": 0,
            "Sound": "",
            "Transition": 0,
            "BGName": 0,
            "BGEffect": 0,
            "PopupFileName": "",
            "ScriptKr": "#st;[-1200,-630];serial;60;[wa:1850]― [log=카즈사 밴드]나도 못 먹으니까![/log]",
            "TextJp": "[wa:1850]― [log=카즈사 밴드]私も食べらんないから！[/log]",
            "VoiceId": 0
          },
          {
            "ByteBuffer": {
              "Position": 0,
              "Length": 96
            },
            "GroupId": 1009103,
            "SelectionGroup": 0,
            "BGMId": 0,
            "Sound": "",
            "Transition": 0,
            "BGName": 0,
            "BGEffect": 0,
            "PopupFileName": "",
            "ScriptKr": "#wait;2280",
            "TextJp": "",
            "VoiceId": 0
          },
          {
            "ByteBuffer": {
              "Position": 0,
              "Length": 96
            },
            "GroupId": 1009103,
            "SelectionGroup": 0,
            "BGMId": 0,
            "Sound": "",
            "Transition": 0,
            "BGName": 0,
            "BGEffect": 0,
            "PopupFileName": "",
            "ScriptKr": "#clearST",
            "TextJp": "",
            "VoiceId": 0
          },
          {
            "ByteBuffer": {
              "Position": 0,
              "Length": 256
            },
            "GroupId": 1009103,
            "SelectionGroup": 0,
            "BGMId": 0,
            "Sound": "",
            "Transition": 0,
            "BGName": 0,
            "BGEffect": 0,
            "PopupFileName": "",
            "ScriptKr": "#st;[-1200,-530];serial;60;[wa:1670]― [log=카즈사 밴드]자, [wa:895]아~[wa:910]![/log]",
            "TextJp": "[wa:1670]― [log=카즈사 밴드]はい、[wa:895]あ～[wa:910]ん！[/log]",
            "VoiceId": 0
          },
          {
            "ByteBuffer": {
              "Position": 0,
              "Length": 96
            },
            "GroupId": 1009103,
            "SelectionGroup": 0,
            "BGMId": 0,
            "Sound": "",
            "Transition": 0,
            "BGName": 0,
            "BGEffect": 0,
            "PopupFileName": "",
            "ScriptKr": "#wait;5775",
            "TextJp": "",
            "VoiceId": 0
          },
          {
            "ByteBuffer": {
              "Position": 0,
              "Length": 96
            },
            "GroupId": 1009103,
            "SelectionGroup": 0,
            "BGMId": 0,
            "Sound": "",
            "Transition": 0,
            "BGName": 0,
            "BGEffect": 0,
            "PopupFileName": "",
            "ScriptKr": "#clearST",
            "TextJp": "",
            "VoiceId": 0
          },
          {
            "ByteBuffer": {
              "Position": 0,
              "Length": 240
            },
            "GroupId": 1009103,
            "SelectionGroup": 0,
            "BGMId": 0,
            "Sound": "",
            "Transition": 0,
            "BGName": 1600671339,
            "BGEffect": 0,
            "PopupFileName": "",
            "ScriptKr": "#st;[-1200,-530];serial;60;[wa:330]― [log=카즈사 밴드]……[wa:1240]응?[/log]",
            "TextJp": "[wa:330]― [log=카즈사 밴드]……[wa:1240]え？[/log]",
            "VoiceId": 0
          },
          {
            "ByteBuffer": {
              "Position": 0,
              "Length": 96
            },
            "GroupId": 1009103,
            "SelectionGroup": 0,
            "BGMId": 0,
            "Sound": "",
            "Transition": 0,
            "BGName": 0,
            "BGEffect": 0,
            "PopupFileName": "",
            "ScriptKr": "#wait;1540",
            "TextJp": "",
            "VoiceId": 0
          },
          {
            "ByteBuffer": {
              "Position": 0,
              "Length": 96
            },
            "GroupId": 1009103,
            "SelectionGroup": 0,
            "BGMId": 0,
            "Sound": "",
            "Transition": 0,
            "BGName": 0,
            "BGEffect": 0,
            "PopupFileName": "",
            "ScriptKr": "#clearST",
            "TextJp": "",
            "VoiceId": 0
          },
          {
            "ByteBuffer": {
              "Position": 0,
              "Length": 200
            },
            "GroupId": 1009103,
            "SelectionGroup": 0,
            "BGMId": 0,
            "Sound": "",
            "Transition": 0,
            "BGName": 0,
            "BGEffect": 0,
            "PopupFileName": "",
            "ScriptKr": "#st;[-1200,-530];serial;60;― [log=카즈사 밴드]괜찮아?[/log]",
            "TextJp": "― [log=카즈사 밴드]大丈夫？[/log]",
            "VoiceId": 0
          },
          {
            "ByteBuffer": {
              "Position": 0,
              "Length": 272
            },
            "GroupId": 1009103,
            "SelectionGroup": 0,
            "BGMId": 0,
            "Sound": "",
            "Transition": 0,
            "BGName": 0,
            "BGEffect": 0,
            "PopupFileName": "",
            "ScriptKr": "#st;[-1200,-630];serial;60;[wa:1810]― [log=카즈사 밴드]먼저[wa:650] 먹으[wa:450]라고...?[/log]",
            "TextJp": "[wa:1810]― [log=카즈사 밴드]先に[wa:650]食べ[wa:450]て……？[/log]",
            "VoiceId": 0
          },
          {
            "ByteBuffer": {
              "Position": 0,
              "Length": 96
            },
            "GroupId": 1009103,
            "SelectionGroup": 0,
            "BGMId": 0,
            "Sound": "",
            "Transition": 0,
            "BGName": 0,
            "BGEffect": 0,
            "PopupFileName": "",
            "ScriptKr": "#wait;9910",
            "TextJp": "",
            "VoiceId": 0
          },
          {
            "ByteBuffer": {
              "Position": 0,
              "Length": 96
            },
            "GroupId": 1009103,
            "SelectionGroup": 0,
            "BGMId": 0,
            "Sound": "",
            "Transition": 0,
            "BGName": 0,
            "BGEffect": 0,
            "PopupFileName": "",
            "ScriptKr": "#clearST",
            "TextJp": "",
            "VoiceId": 0
          },
          {
            "ByteBuffer": {
              "Position": 0,
              "Length": 224
            },
            "GroupId": 1009103,
            "SelectionGroup": 0,
            "BGMId": 0,
            "Sound": "",
            "Transition": 0,
            "BGName": 2958656569,
            "BGEffect": 0,
            "PopupFileName": "",
            "ScriptKr": "#st;[-1200,-530];serial;60;[wa:620]― [log=카즈사 밴드]어……?[/log]",
            "TextJp": "[wa:620]― [log=카즈사 밴드]え……？[/log]",
            "VoiceId": 0
          },
          {
            "ByteBuffer": {
              "Position": 0,
              "Length": 304
            },
            "GroupId": 1009103,
            "SelectionGroup": 0,
            "BGMId": 0,
            "Sound": "",
            "Transition": 0,
            "BGName": 0,
            "BGEffect": 0,
            "PopupFileName": "",
            "ScriptKr": "#st;[-1200,-630];serial;60;[wa:1240]― [log=카즈사 밴드]이 스푼, [wa:1585]카즈사 [wa:860]거고?[/log]",
            "TextJp": "[wa:1240]― [log=카즈사 밴드]このスプーン、[wa:1585]カズサの[wa:860]だし？[/log]",
            "VoiceId": 0
          },
          {
            "ByteBuffer": {
              "Position": 0,
              "Length": 96
            },
            "GroupId": 1009103,
            "SelectionGroup": 0,
            "BGMId": 0,
            "Sound": "",
            "Transition": 0,
            "BGName": 0,
            "BGEffect": 0,
            "PopupFileName": "",
            "ScriptKr": "#wait;1985",
            "TextJp": "",
            "VoiceId": 0
          },
          {
            "ByteBuffer": {
              "Position": 0,
              "Length": 96
            },
            "GroupId": 1009103,
            "SelectionGroup": 0,
            "BGMId": 0,
            "Sound": "",
            "Transition": 0,
            "BGName": 0,
            "BGEffect": 0,
            "PopupFileName": "",
            "ScriptKr": "#clearST",
            "TextJp": "",
            "VoiceId": 0
          },
          {
            "ByteBuffer": {
              "Position": 0,
              "Length": 216
            },
            "GroupId": 1009103,
            "SelectionGroup": 0,
            "BGMId": 0,
            "Sound": "",
            "Transition": 0,
            "BGName": 0,
            "BGEffect": 0,
            "PopupFileName": "",
            "ScriptKr": "#st;[-1200,-530];serial;60;― [log=카즈사 밴드]……[wa:2860]응?[/log]",
            "TextJp": "― [log=카즈사 밴드]……[wa:2860]へ？[/log]",
            "VoiceId": 0
          },
          {
            "ByteBuffer": {
              "Position": 0,
              "Length": 240
            },
            "GroupId": 1009103,
            "SelectionGroup": 0,
            "BGMId": 0,
            "Sound": "",
            "Transition": 0,
            "BGName": 0,
            "BGEffect": 0,
            "PopupFileName": "",
            "ScriptKr": "#st;[-1200,-630];serial;60;[wa:800]― [log=카즈사 밴드]……[wa:1190]어라?[/log]",
            "TextJp": "[wa:800]― [log=카즈사 밴드]……[wa:1190]あれ？[/log]",
            "VoiceId": 0
          },
          {
            "ByteBuffer": {
              "Position": 0,
              "Length": 96
            },
            "GroupId": 1009103,
            "SelectionGroup": 0,
            "BGMId": 0,
            "Sound": "",
            "Transition": 0,
            "BGName": 0,
            "BGEffect": 0,
            "PopupFileName": "",
            "ScriptKr": "#wait;8190",
            "TextJp": "",
            "VoiceId": 0
          },
          {
            "ByteBuffer": {
              "Position": 0,
              "Length": 96
            },
            "GroupId": 1009103,
            "SelectionGroup": 0,
            "BGMId": 0,
            "Sound": "",
            "Transition": 0,
            "BGName": 0,
            "BGEffect": 0,
            "PopupFileName": "",
            "ScriptKr": "#clearST",
            "TextJp": "",
            "VoiceId": 0
          },
          {
            "ByteBuffer": {
              "Position": 0,
              "Length": 240
            },
            "GroupId": 1009103,
            "SelectionGroup": 0,
            "BGMId": 0,
            "Sound": "",
            "Transition": 0,
            "BGName": 1996371531,
            "BGEffect": 0,
            "PopupFileName": "",
            "ScriptKr": "#st;[-1200,-530];serial;60;[wa:1720]― [log=카즈사 밴드]스푼……?[/log]",
            "TextJp": "[wa:1720]― [log=카즈사 밴드]スプーン……？[/log]",
            "VoiceId": 0
          },
          {
            "ByteBuffer": {
              "Position": 0,
              "Length": 224
            },
            "GroupId": 1009103,
            "SelectionGroup": 0,
            "BGMId": 0,
            "Sound": "",
            "Transition": 0,
            "BGName": 0,
            "BGEffect": 0,
            "PopupFileName": "",
            "ScriptKr": "#st;[-1200,-630];serial;60;[wa:2690]― [log=카즈사 밴드]내꺼……?[/log]",
            "TextJp": "[wa:2690]― [log=카즈사 밴드]私の……？[/log]",
            "VoiceId": 0
          },
          {
            "ByteBuffer": {
              "Position": 0,
              "Length": 96
            },
            "GroupId": 1009103,
            "SelectionGroup": 0,
            "BGMId": 0,
            "Sound": "",
            "Transition": 0,
            "BGName": 0,
            "BGEffect": 0,
            "PopupFileName": "",
            "ScriptKr": "#wait;2780",
            "TextJp": "",
            "VoiceId": 0
          },
          {
            "ByteBuffer": {
              "Position": 0,
              "Length": 96
            },
            "GroupId": 1009103,
            "SelectionGroup": 0,
            "BGMId": 0,
            "Sound": "",
            "Transition": 0,
            "BGName": 0,
            "BGEffect": 0,
            "PopupFileName": "",
            "ScriptKr": "#clearST",
            "TextJp": "",
            "VoiceId": 0
          },
          {
            "ByteBuffer": {
              "Position": 0,
              "Length": 232
            },
            "GroupId": 1009103,
            "SelectionGroup": 0,
            "BGMId": 0,
            "Sound": "",
            "Transition": 0,
            "BGName": 0,
            "BGEffect": 0,
            "PopupFileName": "",
            "ScriptKr": "#st;[-1200,-530];serial;60;[wa:330]― [log=카즈사 밴드]……[wa:500]어.[/log]",
            "TextJp": "[wa:330]― [log=카즈사 밴드]……[wa:500]あ。[/log]",
            "VoiceId": 0
          },
          {
            "ByteBuffer": {
              "Position": 0,
              "Length": 96
            },
            "GroupId": 1009103,
            "SelectionGroup": 0,
            "BGMId": 0,
            "Sound": "",
            "Transition": 0,
            "BGName": 0,
            "BGEffect": 0,
            "PopupFileName": "",
            "ScriptKr": "#wait;1380",
            "TextJp": "",
            "VoiceId": 0
          },
          {
            "ByteBuffer": {
              "Position": 0,
              "Length": 96
            },
            "GroupId": 1009103,
            "SelectionGroup": 0,
            "BGMId": 0,
            "Sound": "",
            "Transition": 0,
            "BGName": 0,
            "BGEffect": 0,
            "PopupFileName": "",
            "ScriptKr": "#clearST",
            "TextJp": "",
            "VoiceId": 0
          },
          {
            "ByteBuffer": {
              "Position": 0,
              "Length": 224
            },
            "GroupId": 1009103,
            "SelectionGroup": 0,
            "BGMId": 0,
            "Sound": "",
            "Transition": 0,
            "BGName": 0,
            "BGEffect": 0,
            "PopupFileName": "",
            "ScriptKr": "#st;[-1200,-530];serial;60;― [log=카즈사 밴드]우와아아아!?[/log]",
            "TextJp": "― [log=카즈사 밴드]うわああああぁ！？[/log]",
            "VoiceId": 0
          },
          {
            "ByteBuffer": {
              "Position": 0,
              "Length": 248
            },
            "GroupId": 1009103,
            "SelectionGroup": 0,
            "BGMId": 0,
            "Sound": "",
            "Transition": 0,
            "BGName": 0,
            "BGEffect": 0,
            "PopupFileName": "",
            "ScriptKr": "#st;[-1200,-630];serial;60;[wa:2330]― [log=카즈사 밴드]방금 한 말[wa:380] 취소![/log]",
            "TextJp": "[wa:2250]― [log=카즈사 밴드]今の[wa:460]ナシ！[/log]",
            "VoiceId": 0
          },
          {
            "ByteBuffer": {
              "Position": 0,
              "Length": 96
            },
            "GroupId": 1009103,
            "SelectionGroup": 0,
            "BGMId": 0,
            "Sound": "",
            "Transition": 0,
            "BGName": 0,
            "BGEffect": 0,
            "PopupFileName": "",
            "ScriptKr": "#wait;8340",
            "TextJp": "",
            "VoiceId": 0
          },
          {
            "ByteBuffer": {
              "Position": 0,
              "Length": 112
            },
            "GroupId": 1009103,
            "SelectionGroup": 0,
            "BGMId": 0,
            "Sound": "",
            "Transition": 2482233134,
            "BGName": 1047754314,
            "BGEffect": 0,
            "PopupFileName": "",
            "ScriptKr": "#clearST\n#all;hide",
            "TextJp": "",
            "VoiceId": 0
          }
        ]
      }
    ]
  }
}